musix/__init__.py
musix/config.py
musix/main.py
musix/main_msx.py
musix/msx.py
musix/msx_cli.py
musix/musixli.py
musixli-2.1.0.dist-info/METADATA
musixli-2.1.0.dist-info/RECORD
musixli-2.1.0.dist-info/WHEEL
musixli-2.1.0.dist-info/entry_points.txt
musixli-2.1.0.dist-info/top_level.txt
