Metadata-Version: 2.1
Name: musixli
Version: 2.1.0
Summary: A command line application that lets you search for different artists, albums, songs and their lyrics.
Home-page: UNKNOWN
Author: Yathartha Goel
License: MIT License
Platform: Cross Platform
Classifier: Programming Language :: Python :: 3
Classifier: License :: OSI Approved :: MIT License
Classifier: Operating System :: OS Independent
Requires-Dist: click
Requires-Dist: pymusixmatch
Requires-Dist: prompt-toolkit (==1.0.15)
Requires-Dist: pygments
